lord_of_the_rings_sdk/__init__.py
lord_of_the_rings_sdk-0.0.5.dist-info/LICENSE.txt
lord_of_the_rings_sdk-0.0.5.dist-info/METADATA
lord_of_the_rings_sdk-0.0.5.dist-info/WHEEL
lord_of_the_rings_sdk-0.0.5.dist-info/top_level.txt
lord_of_the_rings_sdk-0.0.5.dist-info/RECORD
