Metadata-Version: 2.1
Name: lord-of-the-rings-sdk
Version: 0.0.5
Summary: Lord of the rings sdk in Python
Home-page: https://github.com/Maxzeno/lord_of_the_rings_sdk
Author: Emmanuel Nwaegunwa
Author-email: emmanuelnwaegunwa@gmail.com
Project-URL: Bug Tracker, https://github.com/Maxzeno/lord_of_the_rings_sdk/issues
Project-URL: repository, https://github.com/Maxzeno/lord_of_the_rings_sdk
Classifier: Programming Language :: Python :: 3
Classifier: License :: OSI Approved :: MIT License
Classifier: Operating System :: OS Independent
Requires-Python: >=3.6
License-File: LICENSE.txt
